<?xml version="1.0" encoding="UTF-8" standalone="yes"?><node artifactManager="be.nabu.eai.module.rest.provider.RESTServiceManager" lastModified="2017-02-22T14:16:26.601+01:00" leaf="true" version="49"><environmentId>hyperion</environmentId><properties/><references>nabu.misc.workflow.Services.getWorkflows</references><references>nabu.utils.List.add</references><references>nabu.misc.workflow.providers.basic.services.getWorkflow</references><references>nabu.management.workflow.configuration</references><references>nabu.misc.workflow.Services.getWorkflow</references><references>nabu.misc.workflow.providers.basic.services.getWorkflows</references><references>nabu.management.workflow.types.instance.workflowList</references><references>java.lang.String</references><references>nabu.utils.String.split</references><references>nabu.utils.types.Property</references></node>